get_ips/__init__.py
get_ips/privateip.py
get_ips/publicip.py
get_ips-1.0.2.dist-info/METADATA
get_ips-1.0.2.dist-info/WHEEL
get_ips-1.0.2.dist-info/top_level.txt
get_ips-1.0.2.dist-info/RECORD
